pyathena/__init__.py
pyathena/_version.py
pyathena/async_cursor.py
pyathena/common.py
pyathena/connection.py
pyathena/converter.py
pyathena/cursor.py
pyathena/error.py
pyathena/formatter.py
pyathena/model.py
pyathena/py.typed
pyathena/result_set.py
pyathena/util.py
pyathena/arrow/__init__.py
pyathena/arrow/async_cursor.py
pyathena/arrow/converter.py
pyathena/arrow/cursor.py
pyathena/arrow/result_set.py
pyathena/arrow/util.py
pyathena/filesystem/__init__.py
pyathena/filesystem/s3.py
pyathena/filesystem/s3_object.py
pyathena/pandas/__init__.py
pyathena/pandas/async_cursor.py
pyathena/pandas/converter.py
pyathena/pandas/cursor.py
pyathena/pandas/result_set.py
pyathena/pandas/util.py
pyathena/polars/__init__.py
pyathena/polars/async_cursor.py
pyathena/polars/converter.py
pyathena/polars/cursor.py
pyathena/polars/result_set.py
pyathena/polars/util.py
pyathena/s3fs/__init__.py
pyathena/s3fs/async_cursor.py
pyathena/s3fs/converter.py
pyathena/s3fs/cursor.py
pyathena/s3fs/reader.py
pyathena/s3fs/result_set.py
pyathena/spark/__init__.py
pyathena/spark/async_cursor.py
pyathena/spark/common.py
pyathena/spark/cursor.py
pyathena/sqlalchemy/__init__.py
pyathena/sqlalchemy/arrow.py
pyathena/sqlalchemy/base.py
pyathena/sqlalchemy/compiler.py
pyathena/sqlalchemy/constants.py
pyathena/sqlalchemy/pandas.py
pyathena/sqlalchemy/polars.py
pyathena/sqlalchemy/preparer.py
pyathena/sqlalchemy/requirements.py
pyathena/sqlalchemy/rest.py
pyathena/sqlalchemy/s3fs.py
pyathena/sqlalchemy/types.py
pyathena/sqlalchemy/util.py
pyathena-3.26.0.dist-info/METADATA
pyathena-3.26.0.dist-info/WHEEL
pyathena-3.26.0.dist-info/entry_points.txt
pyathena-3.26.0.dist-info/licenses/LICENSE
pyathena-3.26.0.dist-info/RECORD
