Metadata-Version: 2.4
Name: PyAthena
Version: 3.26.0
Summary: Python DB API 2.0 (PEP 249) client for Amazon Athena
Project-URL: homepage, https://github.com/laughingman7743/PyAthena/
Project-URL: repository, https://github.com/laughingman7743/PyAthena/
Author-email: laughingman7743 <laughingman7743@gmail.com>
License: Copyright 2017 laughingman7743
License-File: LICENSE
Classifier: Development Status :: 4 - Beta
Classifier: Intended Audience :: Developers
Classifier: License :: OSI Approved :: MIT License
Classifier: Operating System :: OS Independent
Classifier: Programming Language :: Python :: 3
Classifier: Programming Language :: Python :: 3.10
Classifier: Programming Language :: Python :: 3.11
Classifier: Programming Language :: Python :: 3.12
Classifier: Programming Language :: Python :: 3.13
Classifier: Programming Language :: Python :: 3.14
Classifier: Topic :: Database :: Front-Ends
Requires-Python: >=3.10
Requires-Dist: boto3>=1.26.4
Requires-Dist: botocore>=1.29.4
Requires-Dist: fsspec
Requires-Dist: python-dateutil
Requires-Dist: tenacity>=4.1.0
Provides-Extra: arrow
Requires-Dist: pyarrow>=10.0.0; (python_version < '3.14') and extra == 'arrow'
Requires-Dist: pyarrow>=22.0.0; (python_version >= '3.14') and extra == 'arrow'
Provides-Extra: pandas
Requires-Dist: pandas>=1.3.0; (python_version < '3.13') and extra == 'pandas'
Requires-Dist: pandas>=2.3.0; (python_version >= '3.13') and extra == 'pandas'
Provides-Extra: polars
Requires-Dist: polars>=1.0.0; extra == 'polars'
Provides-Extra: sqlalchemy
Requires-Dist: sqlalchemy>=1.0.0; extra == 'sqlalchemy'
